imio.email.dms-0.29.4-py3.11-nspkg.pth
imio/email/dms/__init__.py
imio/email/dms/imap.py
imio/email/dms/main.py
imio/email/dms/utils.py
imio/email/dms/tests/__init__.py
imio/email/dms/tests/test_main.py
imio/email/dms/tests/test_utils.py
imio/email/dms/tests/files/pdf-example-bookmarks-1-2.pdf
imio.email.dms-0.29.4.dist-info/LICENSE.GPL
imio.email.dms-0.29.4.dist-info/LICENSE.rst
imio.email.dms-0.29.4.dist-info/METADATA
imio.email.dms-0.29.4.dist-info/WHEEL
imio.email.dms-0.29.4.dist-info/entry_points.txt
imio.email.dms-0.29.4.dist-info/namespace_packages.txt
imio.email.dms-0.29.4.dist-info/top_level.txt
imio.email.dms-0.29.4.dist-info/RECORD
