Metadata-Version: 2.1
Name: imio.email.dms
Version: 0.29.4
Summary: Package to read emails and send them to DMS
Home-page: https://pypi.python.org/pypi/imio.email.dms
Author: Laurent Lasudry
Author-email: info@affinitic.be
License: GPL version 2
Keywords: Python
Classifier: Development Status :: 5 - Production/Stable
Classifier: Environment :: Console
Classifier: Programming Language :: Python
Classifier: Programming Language :: Python :: 3
Classifier: Programming Language :: Python :: 3.10
Classifier: Operating System :: OS Independent
Classifier: License :: OSI Approved :: GNU General Public License v2 (GPLv2)
Requires-Python: >=3.10, <3.11
License-File: LICENSE.GPL
License-File: LICENSE.rst
Requires-Dist: setuptools
Requires-Dist: docopt
Requires-Dist: zc.lockfile
Requires-Dist: imio.email.parser
Requires-Dist: imio.pyutils
Requires-Dist: requests
Requires-Dist: six
Requires-Dist: configparser
Requires-Dist: pathlib2 ; python_version < "3.0"
